boteval/__init__.py
boteval/__main__.py
boteval/app.py
boteval/bots.py
boteval/config.py
boteval/constants.py
boteval/controller.py
boteval/model.py
boteval/mturk.py
boteval/quickstart.py
boteval/registry.py
boteval/service.py
boteval/transforms.py
boteval/utils.py
boteval/wsgi.py
boteval/example-chat-task/.gitignore
boteval/example-chat-task/__init__.py
boteval/example-chat-task/bots.py
boteval/example-chat-task/chat_topics.json
boteval/example-chat-task/conf.yml
boteval/example-chat-task/instructions.html
boteval/example-chat-task/transforms.py
boteval/example-chat-task/user-agreement.html
boteval/static/css/bootstrap.min.css
boteval/static/img/beep.mp3
boteval/static/img/forkme.svg
boteval/static/img/new_message_beep.mp3
boteval/static/js/bootstrap.bundle.min.js
boteval/static/js/jquery-3.5.1.min.js
boteval/static/js/mycode.js
boteval/static/js/socket.io.min.js
boteval/templates/about.html
boteval/templates/base.html
boteval/templates/login.html
boteval/templates/page.html
boteval/templates/seamlesslogin.html
boteval/templates/admin/config.html
boteval/templates/admin/index.html
boteval/templates/admin/threads.html
boteval/templates/admin/topics.html
boteval/templates/admin/users.html
boteval/templates/admin/mturk/HIT.html
boteval/templates/admin/mturk/HITs.html
boteval/templates/admin/mturk/_macros.html
boteval/templates/admin/mturk/home.html
boteval/templates/admin/mturk/qualification.html
boteval/templates/admin/mturk/qualifications.html
boteval/templates/user/_macros.html
boteval/templates/user/chatui.html
boteval/templates/user/chatui_two_users.html
boteval/templates/user/index.html
boteval/templates/user/mturk_submit.html
boteval-0.1.dist-info/LICENSE
boteval-0.1.dist-info/METADATA
boteval-0.1.dist-info/WHEEL
boteval-0.1.dist-info/entry_points.txt
boteval-0.1.dist-info/top_level.txt
boteval-0.1.dist-info/RECORD
